LICENCE
README.md
setup.py
wilder/__init__.py
wilder/eda.py
wilder.egg-info/PKG-INFO
wilder.egg-info/SOURCES.txt
wilder.egg-info/dependency_links.txt
wilder.egg-info/requires.txt
wilder.egg-info/top_level.txt